bytedance_aikb_auth_knowledge/__init__.py
bytedance_aikb_auth_knowledge-0.0.1.dist-info/METADATA
bytedance_aikb_auth_knowledge-0.0.1.dist-info/WHEEL
bytedance_aikb_auth_knowledge-0.0.1.dist-info/top_level.txt
bytedance_aikb_auth_knowledge-0.0.1.dist-info/RECORD
